{
    "id": 128491743,
    "name": "DRAMAtic Tacos",
    "author": "Jascow",
    "creators": [],
    "verifier": "Jascow",
    "verification": "https://www.youtube.com/watch?v=EOFIAyztv9o",
    "percentToQualify": "100",
    "password": "Free To Copy",
    "records": [
        {
            "user": "finni1505",
            "link": "https://medal.tv/de/games/geometry-dash/clips/lzBHGBC8NFZl96pi1?invite=cr-MSw1Z1IsMzY5MjUzOTQw&v=19",
            "percent": 100,
            "hz": 240
        },
        {
            "user": "Cramble",
            "link": "https://www.youtube.com/watch?v=NjKR5kW0Y0s",
            "percent": 100,
            "hz": 240
        }
    ]

}


